vsrc/f2i.v
module f2i (a,d,p_lost,denorm,invalid);	// convert float to integer
	input [31:0] a;			// float
	output [31:0] d;		// integer
	output p_lost;			// precision lost
	output denorm;			// if a is a denormalized number, the denorm signal outputs a 1
	output invalid;			// inf,nan,out_of_range
	
	reg [31:0] d;			// will be combinational
	reg p_lost;			// will be combinational
	reg invalid;			// will be combinational
	wire hidden_bit = |a[30:23];	// hidden bit: the result of operation "|" for each bit of the bus "a" 
	wire frac_is_not_0 = |a[22:0];
	assign denorm = ~hidden_bit & frac_is_not_0;	// denorm:biased exponent=all 0 bits;fraction=anything except all 0 bits
	wire is_zero = ~hidden_bit & ~frac_is_not_0;	// zero:biased exponene and fraction=all 0 bits
	wire sign = a[31];
	wire [8:0] shift_right_bits = 9'd158 - {1'b0, a[30:23]};	// shift to right by 158(127+31)-e_a bits
	wire [55:0] frac0 = {hidden_bit, a[22:0], 32'h0};	// 32+24 = 56bits
	wire [55:0] f_abs = ($signed(shift_right_bits)>9'd32)?frac0 >> 6'd32 : frac0 >> shift_right_bits; // shift; $signed(c) can change c to signed
	wire lost_bits = |f_abs[23:0];	// if != 0, p_lost = 1
	wire [31:0] int32 = sign?~f_abs[55:24] + 32'd1 : f_abs[55:24];

	always @ * begin
		if (denorm) begin
			p_lost = 1;
			invalid = 0;
			d = 32'h00000000;
		end 
		else begin
			if (shift_right_bits[8]) begin
				p_lost = 0;
				invalid = 1;
				d = 32'h80000000;
			end
		       	else begin
				if (shift_right_bits[7:0]>8'h1f) begin
					if (is_zero) p_lost = 0;
					else p_lost = 1;
					invalid = 0;
					d = 32'h00000000;
				end 
				else begin
					if (sign != int32[31]) begin
						p_lost = 0;
						invalid = 1;
						d = 32'h80000000;
					end 
					else begin
						if (lost_bits) p_lost = 1;
						else p_lost = 0;
						invalid = 0;
						d = int32;
					end
				end
			end
		end
	end
endmodule

obj_dir/wave.vcd
$version Generated by VerilatedVcd $end
$timescale 1ps $end

 $scope module TOP $end
  $var wire 32 ) a [31:0] $end
  $var wire 32 * d [31:0] $end
  $var wire  1 , denorm $end
  $var wire  1 - invalid $end
  $var wire  1 + p_lost $end
  $scope module f2i $end
   $var wire 32 ) a [31:0] $end
   $var wire 32 * d [31:0] $end
   $var wire  1 , denorm $end
   $var wire 56 % f_abs [55:0] $end
   $var wire 56 # frac0 [55:0] $end
   $var wire  1 / frac_is_not_0 $end
   $var wire  1 . hidden_bit $end
   $var wire 32 ( int32 [31:0] $end
   $var wire  1 - invalid $end
   $var wire  1 0 is_zero $end
   $var wire  1 ' lost_bits $end
   $var wire  1 + p_lost $end
   $var wire  9 2 shift_right_bits [8:0] $end
   $var wire  1 1 sign $end
  $upscope $end
 $upscope $end
$enddefinitions $end


#0
b11111111111111111111111100000000000000000000000000000000 #
b01111111111111111111111110000000000000000000000000000000 %
0'
b01111111111111111111111110000000 (
b01001110111111111111111111111111 )
b01111111111111111111111110000000 *
0+
0,
0-
1.
1/
00
01
b000000001 2
#1
b10000000000000000000000000000000000000000000000000000000 #
b10000000000000000000000000000000000000000000000000000000 %
b10000000000000000000000000000000 (
b01001111000000000000000000000000 )
b10000000000000000000000000000000 *
1-
0/
b000000000 2
#2
b00000000000000000000000000000001000000000000000000000000 %
b00000000000000000000000000000001 (
b00111111100000000000000000000000 )
b00000000000000000000000000000001 *
0-
b000011111 2
#3
b00000000000000000000000000000000100000000000000000000000 %
1'
b00000000000000000000000000000000 (
b00111111000000000000000000000000 )
b00000000000000000000000000000000 *
1+
b000100000 2
#4
b00000000000000000000000100000000000000000000000000000000 #
b00000000000000000000000000000000000000000000000000000001 %
b00000000000000000000000000000001 )
1,
0.
1/
b010011110 2
#5
b10000000000000000000000000000000000000000000000000000000 #
b00000000000000000000000000000000100000000000000000000000 %
b01111111100000000000000000000000 )
b10000000000000000000000000000000 *
0+
0,
1-
1.
0/
b110011111 2
#6
b11000000000000000000000000000000000000000000000000000000 #
b00000000000000000000000000000001100000000000000000000000 %
b00000000000000000000000000000001 (
b00111111110000000000000000000000 )
b00000000000000000000000000000001 *
1+
0-
1/
b000011111 2
#7
b10000000000000000000000000000000000000000000000000000000 #
b10000000000000000000000000000000000000000000000000000000 %
0'
b10000000000000000000000000000000 (
b11001111000000000000000000000000 )
b10000000000000000000000000000000 *
0+
0/
11
b000000000 2
#8
b10000000000000000000000100000000000000000000000000000000 #
b10000000000000000000000100000000000000000000000000000000 %
b01111111111111111111111100000000 (
b11001111000000000000000000000001 )
1-
1/
#9
b10000000000000000000000000000000000000000000000000000000 #
b00000000000000000000000000000001000000000000000000000000 %
b11111111111111111111111111111111 (
b10111111100000000000000000000000 )
b11111111111111111111111111111111 *
0-
0/
b000011111 2
#10
b11111111111111111111111100000000000000000000000000000000 #
b00000000000000000000000000000000111111111111111111111111 %
1'
b00000000000000000000000000000000 (
b10111111011111111111111111111111 )
b00000000000000000000000000000000 *
1+
1/
b000100000 2
#11
b00000000000000000000000100000000000000000000000000000000 #
b00000000000000000000000000000000000000000000000000000001 %
b10000000000000000000000000000001 )
1,
0.
b010011110 2
#12
b10000000000000000000000000000000000000000000000000000000 #
b00000000000000000000000000000000100000000000000000000000 %
b11111111100000000000000000000000 )
b10000000000000000000000000000000 *
0+
0,
1-
1.
0/
b110011111 2
#13
b00000000000000000000000000000000000000000000000000000000 #
b00000000000000000000000000000000000000000000000000000000 %
0'
b00000000000000000000000000000000 )
b00000000000000000000000000000000 *
0-
0.
10
01
b010011110 2
